clad/__init__.py
clad/clad.py
clad/constants.py
clad/git.py
clad/logs.py
clad/repos.py
clad/utils.py
clad-0.3.dist-info/DESCRIPTION.rst
clad-0.3.dist-info/METADATA
clad-0.3.dist-info/RECORD
clad-0.3.dist-info/WHEEL
clad-0.3.dist-info/entry_points.txt
clad-0.3.dist-info/metadata.json
clad-0.3.dist-info/top_level.txt
