Metadata-Version: 2.0
Name: clad
Version: 0.3
Summary: Cloudify dev/test environment assistant
Home-page: UNKNOWN
Author: Pavel Brodsky
Author-email: mcouthon@gmail.com
License: Apache License, Version 2.0
Platform: UNKNOWN
Requires-Dist: argh (>=0.26.2)
Requires-Dist: sh (>=1.12.14)
Requires-Dist: colorama (>=0.3.9)
